tuckboxes/__init__.py
tuckboxes/tuckboxes.py
tuckboxes-0.0.1.dist-info/LICENSE.md
tuckboxes-0.0.1.dist-info/METADATA
tuckboxes-0.0.1.dist-info/WHEEL
tuckboxes-0.0.1.dist-info/entry_points.txt
tuckboxes-0.0.1.dist-info/top_level.txt
tuckboxes-0.0.1.dist-info/RECORD
