Metadata-Version: 2.1
Name: tuckboxes
Version: 0.0.1
Summary: Tuckbox Generation for Board- and Cardgames
Home-page: http://domtabs.sandflea.org
Author: Peter Gorniak
Author-email: sumpfork@mailmight.net
License: UNKNOWN
Keywords: boardgame,cardgame,tuckboxes
Platform: UNKNOWN
Requires-Dist: reportlab (>=3.4.0)
Requires-Dist: Pillow (>=4.1.0)
Requires-Dist: numpy
